{
  "sentinel_health": {
    "WeatherSentinel": {
      "data": {
        "status": "OK",
        "last_check_utc": "2026-03-17T11:30:44.484495+00:00",
        "interval_seconds": 14400,
        "error": null
      },
      "timestamp": 1773747044.485254
    },
    "LogisticsSentinel": {
      "data": {
        "status": "OK",
        "last_check_utc": "2026-03-17T13:30:47.297004+00:00",
        "interval_seconds": 21600,
        "error": null
      },
      "timestamp": 1773754247.298323
    },
    "NewsSentinel": {
      "data": {
        "status": "OK",
        "last_check_utc": "2026-03-17T13:33:02.656611+00:00",
        "interval_seconds": 7200,
        "error": null
      },
      "timestamp": 1773754382.659104
    },
    "XSentimentSentinel": {
      "data": {
        "status": "OK",
        "last_check_utc": "2026-03-17T15:02:51.511310+00:00",
        "interval_seconds": 5400,
        "error": null
      },
      "timestamp": 1773759771.5121293
    },
    "PredictionMarketSentinel": {
      "data": {
        "status": "OK",
        "last_check_utc": "2026-03-17T15:29:02.746617+00:00",
        "interval_seconds": 300,
        "error": null
      },
      "timestamp": 1773761342.7475538
    },
    "MacroContagionSentinel": {
      "data": {
        "status": "OK",
        "last_check_utc": "2026-03-17T11:31:04.789289+00:00",
        "interval_seconds": 14400,
        "error": null
      },
      "timestamp": 1773747064.7901204
    },
    "PriceSentinel": {
      "data": {
        "status": "OK",
        "last_check_utc": "2026-03-17T15:30:02.885660+00:00",
        "interval_seconds": 60,
        "error": null
      },
      "timestamp": 1773761402.8876834
    },
    "MicrostructureSentinel": {
      "data": {
        "status": "OK",
        "last_check_utc": "2026-03-17T15:30:02.906705+00:00",
        "interval_seconds": 60,
        "error": null
      },
      "timestamp": 1773761402.9100688
    }
  },
  "prediction_market_state": {
    "Fed decision in March?": {
      "data": {
        "severity_hwm": 0,
        "hwm_timestamp": null,
        "slug": "fed-decision-in-march-885",
        "title": "Fed decision in March?",
        "market_id": "0x25aa90b3cd98305e849189b4e8b770fc77fe89bccb7cf9656468414e01145d38",
        "price": 0.0005,
        "timestamp": "2026-03-17T15:29:01.437293+00:00",
        "failure_count": 0
      },
      "timestamp": 1773761342.742085
    },
    "Fed decision in April?": {
      "data": {
        "severity_hwm": 0,
        "hwm_timestamp": null,
        "slug": "fed-decision-in-april",
        "title": "Fed decision in April?",
        "market_id": "0xd72622d154dfe65b9c019d6afcfe75a55717e5c502db611f555b101aafbf6ec5",
        "price": 0.0105,
        "timestamp": "2026-03-17T15:29:01.463202+00:00",
        "failure_count": 0
      },
      "timestamp": 1773761342.7420888
    },
    "How many Fed rate cuts in 2026?": {
      "data": {
        "severity_hwm": 0,
        "hwm_timestamp": null,
        "slug": "how-many-fed-rate-cuts-in-2026",
        "title": "How many Fed rate cuts in 2026?",
        "market_id": "0x1adf074e048fa613f4ddbc0766088748a48d120a3a713b0183e219032a411ae3",
        "price": 0.0025,
        "timestamp": "2026-03-17T15:29:01.883696+00:00",
        "failure_count": 0
      },
      "timestamp": 1773761342.742091
    },
    "Fed decisions (Dec-Mar)": {
      "data": {
        "severity_hwm": 0,
        "hwm_timestamp": null,
        "slug": "next-three-fed-decisions-847",
        "title": "Fed decisions (Dec-Mar)",
        "market_id": "0x4b23c2e3ee806915cc1186641d292acbc6b26d7a7746ee93c910b8b0c87d4bca",
        "price": 0.995,
        "timestamp": "2026-03-17T15:29:01.480676+00:00",
        "failure_count": 0
      },
      "timestamp": 1773761342.7420926
    },
    "Russia x Ukraine ceasefire by end of 2026?": {
      "data": {
        "severity_hwm": 0,
        "hwm_timestamp": null,
        "slug": "russia-x-ukraine-ceasefire-before-2027",
        "title": "Russia x Ukraine ceasefire by end of 2026?",
        "market_id": "0xaeea5f917fc5746387b5f9c0a4263dba035dbb3f0ac6ad72bf92183d21e26739",
        "price": 0.365,
        "timestamp": "2026-03-17T15:29:01.683986+00:00",
        "failure_count": 0
      },
      "timestamp": 1773761342.7420945
    },
    "Russia x Ukraine ceasefire by March 31, 2026?": {
      "data": {
        "severity_hwm": 0,
        "hwm_timestamp": null,
        "slug": "russia-x-ukraine-ceasefire-by-march-31-2026",
        "title": "Russia x Ukraine ceasefire by March 31, 2026?",
        "market_id": "0x1d54eb5eac2cee8f595f3097c65da7d07f8ab5dee63d7c0c6883eb70e1e9af30",
        "price": 0.0165,
        "timestamp": "2026-03-17T15:29:01.863485+00:00",
        "failure_count": 0
      },
      "timestamp": 1773761342.7420964
    },
    "Fed emergency rate cut before 2027?": {
      "data": {
        "severity_hwm": 0,
        "hwm_timestamp": null,
        "slug": "fed-emergency-rate-cut-before-2027",
        "title": "Fed emergency rate cut before 2027?",
        "market_id": "0x93a3b80b1fb485057add882b55d12011ea011fedd9abededad86ac6cb53a2802",
        "price": 0.18,
        "timestamp": "2026-03-17T15:29:01.900138+00:00",
        "failure_count": 0
      },
      "timestamp": 1773761342.7420983
    },
    "Putin out as President of Russia by end of 2026?": {
      "data": {
        "severity_hwm": 0,
        "hwm_timestamp": null,
        "slug": "putin-out-before-2027",
        "title": "Putin out as President of Russia by end of 2026?",
        "market_id": "0x6bd56627aa21311850825edb27e53434a0e17a4f782be0086bc07f71eee00d0d",
        "price": 0.115,
        "timestamp": "2026-03-17T15:29:02.377090+00:00",
        "failure_count": 0
      },
      "timestamp": 1773761342.7421002
    },
    "US recession by end of 2026?": {
      "data": {
        "severity_hwm": 0,
        "hwm_timestamp": null,
        "slug": "us-recession-by-end-of-2026",
        "title": "US recession by end of 2026?",
        "market_id": "0xfdc73f10edf0266756686f35b5712cffa828b0940fc015e0426c76c934c2105d",
        "price": 0.305,
        "timestamp": "2026-03-17T15:29:02.552047+00:00",
        "failure_count": 0
      },
      "timestamp": 1773761342.7421014
    },
    "Iran Nuke before 2027?": {
      "data": {
        "severity_hwm": 0,
        "hwm_timestamp": null,
        "slug": "iran-nuke-before-2027",
        "title": "Iran Nuke before 2027?",
        "market_id": "0x8bdeac60c92d3bc494792fd334ca181b0cf70355f23dca4098d558280b554c81",
        "price": 0.14,
        "timestamp": "2026-03-17T15:29:02.741029+00:00",
        "failure_count": 0
      },
      "timestamp": 1773761342.7421033
    },
    "Which countries will Trump make new trade deals with before 2027?": {
      "data": {
        "severity_hwm": 0,
        "hwm_timestamp": null,
        "slug": "which-countries-will-trump-make-new-trade-deals-with-before-2027-921",
        "title": "Which countries will Trump make new trade deals with before 2027?",
        "market_id": "0x42520d88b4fa9d58ea74d3579b14398e76873a88c09bbfc9e0e801694a547d5c",
        "price": 0.212,
        "timestamp": "2026-03-17T15:29:01.920600+00:00",
        "failure_count": 0
      },
      "timestamp": 1773761342.7421055
    }
  },
  "sensors": {
    "NG_sentinel_ib_status": {
      "data": "CONNECTED",
      "timestamp": 1773732611.3554564
    },
    "last_ib_success": {
      "data": "2026-03-17T14:12:30.848564+00:00",
      "timestamp": 1773756750.8499844
    },
    "NG_microstructure_ib_status": {
      "data": "CONNECTED",
      "timestamp": 1773732614.0673318
    },
    "NG_sentinel_last_error": {
      "data": "[Errno 111] Connect call failed ('127.0.0.1', 4001)",
      "timestamp": 1773621509.3342776
    },
    "last_ib_failure": {
      "data": "2026-03-16T00:38:29.333579+00:00",
      "timestamp": 1773621509.3342788
    },
    "NG_cleanup_ib_status": {
      "data": "CONNECTED",
      "timestamp": 1773751500.190172
    },
    "x_sentiment": {
      "data": {
        "sentiment_sensor_status": "ONLINE",
        "consecutive_failures": 0,
        "degraded_until": null,
        "spend_cap_until": null
      },
      "timestamp": 1773759771.5058599
    },
    "NG_drawdown_check_ib_status": {
      "data": "CONNECTED",
      "timestamp": 1773756360.4261324
    },
    "NG_orchestrator_orders_ib_status": {
      "data": "CONNECTED",
      "timestamp": 1773756750.8499794
    }
  },
  "sentinel_history": {
    "events": {
      "data": [
        {
          "source": "MicrostructureSentinel",
          "reason": "Liquidity Depletion: 32% of average",
          "payload": {
            "type": "LIQUIDITY_DEPLETION",
            "contract": "NGM26",
            "depth_ratio": 0.3215077605321508
          },
          "timestamp": "2026-03-17T13:15:41.128296+00:00"
        },
        {
          "source": "MicrostructureSentinel",
          "reason": "Liquidity Depletion: 31% of average",
          "payload": {
            "type": "LIQUIDITY_DEPLETION",
            "contract": "NGM26",
            "depth_ratio": 0.3091684434968017
          },
          "timestamp": "2026-03-17T13:31:57.045268+00:00"
        },
        {
          "source": "MicrostructureSentinel",
          "reason": "Liquidity Depletion: 17% of average",
          "payload": {
            "type": "LIQUIDITY_DEPLETION",
            "contract": "NGM26",
            "depth_ratio": 0.16893203883495148
          },
          "timestamp": "2026-03-17T13:46:07.883700+00:00"
        },
        {
          "source": "MicrostructureSentinel",
          "reason": "Liquidity Depletion: 27% of average",
          "payload": {
            "type": "LIQUIDITY_DEPLETION",
            "contract": "NGM26",
            "depth_ratio": 0.2695167286245353
          },
          "timestamp": "2026-03-17T14:18:25.941746+00:00"
        },
        {
          "source": "MicrostructureSentinel",
          "reason": "Liquidity Depletion: 23% of average",
          "payload": {
            "type": "LIQUIDITY_DEPLETION",
            "contract": "NGM26",
            "depth_ratio": 0.22906793048973143
          },
          "timestamp": "2026-03-17T14:59:41.959645+00:00"
        }
      ],
      "timestamp": 1773759581.9603522
    }
  },
  "reports": {
    "agronomist": {
      "data": {
        "data": "[EVIDENCE]: 1. U.S. Lower 48 gas output rose to 110.0 Bcf/d in March, up from 109.2 Bcf/d in February. 2. Permian associated gas production is averaging 27.7 Bcf/d, prompting the EIA to revise Permian production estimates upward by 0.8 Bcf/d for 2025-2026. 3. Waha Hub spot prices remained negative for a record 27th consecutive day due to Permian pipeline constraints. 4. The U.S. gas rig count increased by 1 to 133, and Summit Midstream reported ~90 DUC wells providing a buffer for future volume growth. 5. Storage inventories sit at 1,848 Bcf, which is 8.3% above last year, neutralizing supply tightness concerns.\n[ANALYSIS]: The previous analysis contained a hallucinated variable ('mild weather') not supported by the evidence and slightly conflated localized Waha Hub constraints with national Henry Hub bearishness (trapped Permian gas actually restricts supply to the broader market, though overall production is still rising). A revised assessment confirms a bearish outlook for Henry Hub based strictly on the provided data. U.S. Lower 48 production is expanding, reaching 110.0 Bcf/d, heavily supported by Permian associated gas. While pipeline constraints have trapped gas locally in West Texas, the broader macro picture remains oversupplied. Storage levels are 8.3% higher year-over-year (1,848 Bcf), eliminating near-term supply risk. Furthermore, the slight uptick in gas rigs and a healthy DUC inventory indicate producers can easily maintain or accelerate output, capping potential price rallies.\n[CONFIDENCE]: 0.8\n[SENTIMENT TAG]: [SENTIMENT: BEARISH]",
        "confidence": 0.8,
        "sentiment": "BEARISH"
      },
      "timestamp": 1773756738.0468738
    },
    "macro": {
      "data": {
        "data": "[EVIDENCE]: - [2026-03-16 | Zacks Investment Research] Total U.S. natural gas demand fell 10% week-over-week; residential/commercial demand fell 27%.\n- [2026-03-17 | Industrial Info Resources] Feedgas to nine U.S. LNG export facilities averaged 19.5 Bcf/d, near the 19.6 Bcf/d record set in January.\n- [2026-03-16 | Zacks Investment Research] 36 LNG vessels departed U.S. terminals in the latest week with combined carrying capacity of 133 Bcf.\n- [2026-03-16 | Marine Log] U.S. Secretary of Energy authorized an immediate 13% (0.45 Bcf/d) increase in LNG exports from the Plaquemines terminal.\n- [2026-03-17 | Business Recorder citing LSEG] April natural gas futures fell to $3.116/MMBtu; average U.S. output rose to 110.0 Bcf/d in March; Waha Hub cash prices were negative for a record 27th consecutive day due to Permian pipeline constraints.\n[ANALYSIS]: Self-critique of the prior analysis (key weaknesses):\n1) Potential fallacies / reasoning issues:\n- Mild recency bias: The conclusion leans heavily on a single week\u2019s demand change (10% w/w, res/comm -27%), which can be noisy due to short-term weather swings or reporting effects.\n- Risk of false causation: Interpreting the demand drop as \u201cshoulder season\u201d is plausible, but the packet provides no HDD/CDD data. The correct claim is simply that space-heating-linked demand declined; the meteorological attribution should remain tentative.\n- Overweighting regional constraint signal: Negative Waha pricing is a strong indicator of Permian takeaway constraints, but it does not mechanically translate one-for-one into Henry Hub bearishness; it is a regional basis phenomenon that can coexist with tighter balances elsewhere.\n2) Source specificity:\n- The prior analysis generally cited specific figures and outlets (Zacks, Industrial Info Resources, Marine Log, LSEG via Business Recorder). That is good.\n- However, a few statements were more interpretive than directly evidenced (e.g., \u201cdominant near-term signal aligns with softer demand plus higher production\u201d is reasonable but should be framed as an inference and bounded by missing storage and weather data).\n3) Sentiment tag justification:\n- A bearish lean is defensible based on (a) rising production to 110.0 Bcf/d, (b) a large w/w drop in total demand, and (c) contemporaneous futures price decline to $3.116.\n- But it should be tempered by clearly supportive LNG evidence: feedgas near record (19.5 Bcf/d), substantial liftings (36 cargoes/133 Bcf capacity), and incremental authorization at Plaquemines (+0.45 Bcf/d). Without storage/inventory, forward curve context, or sustained multi-week demand/supply trends, conviction should be moderate rather than strong.\n\nRevised improved analysis:\nNear-term U.S. gas fundamentals in the packet present a mixed-to-soft picture for Henry Hub. On the bearish side, total U.S. demand fell 10% week-over-week, driven by a sharp 27% drop in residential/commercial consumption (Zacks), and average March output increased to 110.0 Bcf/d (LSEG via Business Recorder). These two datapoints, taken together, imply looser balances versus the prior week. The market action is directionally consistent with that setup: April futures declined to $3.116/MMBtu (LSEG/Business Recorder).\n\nOffsetting that, LNG export pull is strong and potentially strengthening: feedgas to nine export facilities reached 19.5 Bcf/d, near the historical record (Industrial Info Resources), and weekly liftings were high (36 departures; 133 Bcf carrying capacity, Zacks). Policy is also supportive at the margin via the immediate Plaquemines authorization increase (+0.45 Bcf/d, Marine Log), which\u2014if utilized\u2014adds incremental demand for U.S. feedgas relative to a no-change baseline.\n\nRegionally, persistent negative Waha pricing for 27 consecutive days (LSEG/Business Recorder) signals acute Permian takeaway constraints and localized oversupply. This is bearish for that basis market and can weigh on the broader complex via associated-gas growth, but it should be treated primarily as a regional constraint indicator rather than definitive proof of Henry Hub oversupply.\n\nBottom line: With the evidence provided (and absent HDD/CDD, storage, or power-burn/industrial indicators), the balance of signals leans slightly bearish for Henry Hub in the near term because production is rising while a key demand segment fell sharply week-over-week; strong LNG flows and supportive policy partially offset but do not clearly dominate within this limited dataset.\n[CONFIDENCE]: 0.65\n[SENTIMENT TAG]: [SENTIMENT: BEARISH]",
        "confidence": 0.65,
        "sentiment": "BEARISH"
      },
      "timestamp": 1773756738.0468802
    },
    "geopolitical": {
      "data": {
        "data": "[EVIDENCE]: 1. U.S. DOE authorized an immediate 0.45 Bcf/d increase in LNG exports from the Plaquemines terminal to non-FTA countries. 2. EU gas storage levels have fallen to 18%, the lowest since 2018, with TTF prices forecast to reach \u20ac57-84/MWh. 3. Asian spot LNG (JKM) reached $20/MMBtu, incentivizing cargo diversions to Asia. 4. The EU confirmed it will not reconsider its ban on Russian LNG despite the loss of ~20% of global LNG capacity from the Strait of Hormuz closure.\n[ANALYSIS]: The previous analysis correctly identified the severe global supply deficit caused by the Strait of Hormuz closure and the resulting intense competition between European and Asian markets. However, it suffered from a logical fallacy by assuming a 'massive structural demand pull' globally would translate linearly to 'strong upward pressure' on U.S. Henry Hub prices, ignoring the physical bottleneck of U.S. LNG export capacity. The U.S. DOE's authorization of an additional 0.45 Bcf/d from Plaquemines will directly increase domestic feedgas demand and tighten the U.S. balance at the margin. Yet, because U.S. export capacity has a hard physical ceiling, the primary price explosion will remain isolated to global indices (TTF and JKM). Domestic prices will experience steady upward pressure due to maximized terminal utilization and the incremental 0.45 Bcf/d draw, but Henry Hub remains partially insulated from the full magnitude of the global price shock. The sentiment remains bullish for U.S. natural gas, but with a more realistic assessment of domestic constraints.\n[CONFIDENCE]: 0.8\n[SENTIMENT TAG]: [SENTIMENT: BULLISH]",
        "confidence": 0.8,
        "sentiment": "BULLISH"
      },
      "timestamp": 1773756738.0468838
    },
    "supply_chain": {
      "data": {
        "data": "[EVIDENCE]: - [2026-03-16] Southern Natural Gas Company implemented Type 3 Level 1 OFOs for its North and South systems effective until further notice (Kinder Morgan). North system connects Perryville hub (near Henry Hub) to Southeast markets.\n- [2026-03-12] Transcontinental Gas Pipe Line Company (Transco) updated its 2026 major construction and maintenance schedule, adding specific pipeline inspection (ILI) activities, which may necessitate temporary flow reductions (Williams).\n- [2026-03-13] LNG feedgas nominations reached an all-time high of approximately 20 Bcf/d (Natural Gas Intelligence).\n- [2026-03-16] U.S. LNG export activity remained strong with 36 vessels carrying approximately 133 Bcf departing terminals in the latest week (Zacks Investment Research).\n- [2026-03-16] Waha hub prices plunged to negative $3.810/MMBtu due to egress constraints, while Henry Hub at $3.09/MMBtu (Natural Gas Intelligence, Trading Economics).\n- Storage withdrawal of 38 Bcf left inventories at 1,848 Bcf (near 5-year average).\n[ANALYSIS]: No major logical fallacies identified: evidence is recent but spans key events without cherry-picking; causation is correlative (constraints + demand = tighter balance) not falsely causal. Sources are specific and cited throughout. Sentiment justified by supply constraints (SNG OFOs limiting Southeast flows from Perryville/Henry Hub area, Transco ILI risks, Permian egress limits reducing Gulf inflows) amid surging LNG demand (20 Bcf/d feedgas, strong exports), with neutral storage. Revised for precision: SNG North OFOs signal localized capacity strain at Perryville (supply bottleneck for regional outflows); overall implies tighter Henry Hub-area balance supporting higher prices.\n[CONFIDENCE]: 0.8\n[SENTIMENT TAG]: [SENTIMENT: BULLISH]",
        "confidence": 0.8,
        "sentiment": "BULLISH"
      },
      "timestamp": 1773756738.0468867
    },
    "inventory": {
      "data": {
        "data": "[EVIDENCE]: 1. [2026-03-12] EIA reported working gas in storage at 1,848 Bcf for week ending March 6, 2026 \u2014 net withdrawal of 38 Bcf, approximately 59% of the 5-year average withdrawal of ~64 Bcf for the same period, and below market expectation of 42 Bcf (source: EIA). 2. [2026-03-12] Storage sits 17 Bcf (0.9%) below the 5-year average of 1,865 Bcf, while remaining 141 Bcf (8.3%) above year-ago levels (source: EIA / Oil & Gas 360). 3. [2026-03-12] Regional breakdown: East (-28 Bcf), Midwest (-22 Bcf) drove withdrawals; South Central and Pacific recorded slight net injections \u2014 an early injection signal in producing regions (source: EIA). 4. [2026-03-13] Baker Hughes natural gas rig count rose 1 to 133 for week ending March 13; total U.S. rig count 553, down significantly year-over-year (source: Baker Hughes). 5. [2026-03-11] NYMEX April natural gas futures closed at $3.21/MMBtu; $0.19 session gain attributed to Middle East geopolitical tension, not domestic fundamentals; Lower 48 production ~109-110 Bcf/d; LNG feedgas ~20 Bcf/d (source: Energy Edge Consulting). DATA STALENESS: All evidence dated March 11-13, 2026; gather timestamp March 17, 2026 \u2014 approximately 4-5 days stale. No EIA report covering week ending March 13, 2026 is present in this packet.\n[ANALYSIS]: SELF-CRITIQUE OF PRIOR ANALYSIS:\n\n(A) LOGICAL FALLACIES IDENTIFIED:\n1. CONFIRMATION BIAS \u2014 The prior analysis acknowledged bearish signals across every data point while underweighting or dismissing bullish offsets (LNG demand floor, rig count YoY decline, geopolitical premium) as 'already priced in' without evidence that they are fully priced. Labeling bullish factors as priced-in without forward curve data is an assertion, not a finding.\n2. RECENCY BIAS \u2014 A single week of below-average withdrawals is treated as a 'dominant signal' for the entire injection season trajectory. One data point cannot establish a trend; the prior analysis overstated its predictive weight.\n3. FALSE PRECISION \u2014 Projecting that the 5-year deficit will 'flip to surplus within 1-2 injection weeks' is a forward projection unsupported by injection pace data or weather forecasts within this evidence packet. This is extrapolation presented as near-certainty.\n4. FALSE CAUSATION RISK \u2014 The $0.19 session gain is attributed to Middle East tensions based on a single secondary source (Energy Edge Consulting), not verified by corroborating price data or positioning data. Accepting this attribution uncritically is a causation assumption.\n5. STRUCTURAL OVERCONFIDENCE \u2014 Asserting that 141 Bcf YoY surplus is 'the most important structural data point' without weighting it against demand-side uncertainty (weather, industrial demand, power burn) reflects selective emphasis.\n\n(B) SOURCE QUALITY:\nSources are specifically cited with dates and origin (EIA, Baker Hughes, Oil & Gas 360, Energy Edge Consulting). This is adequate. However, Energy Edge Consulting is a secondary interpretive source, not a primary price data source, and the geopolitical attribution claim should carry a caveat. No forward curve data, weather forecasts, or power burn data are present \u2014 these are material gaps acknowledged but not fully weighted in the prior analysis.\n\n(C) SENTIMENT JUSTIFICATION ASSESSMENT:\nThe BEARISH tag is directionally supported by the evidence: below-average draws, robust production, early regional injections, and a large YoY surplus are genuinely bearish fundamentals. However, the confidence of 0.25 and the BEARISH tag create an internal tension \u2014 if confidence is that low due to staleness, the sentiment tag should reflect greater uncertainty. A BEARISH tag implies directional conviction; 0.25 confidence implies near-agnosticism. The prior analysis resolves this tension insufficiently.\n\nREVISED FUNDAMENTAL ASSESSMENT:\n\n(1) STORAGE TRAJECTORY \u2014 MODERATELY BEARISH: The 38 Bcf withdrawal (~59% of 5-year average) is a bearish data point for a single week but should not be extrapolated into a seasonal trend without additional weeks of confirmation. It is a signal, not a trend.\n\n(2) 5-YEAR DEFICIT \u2014 NEGLIGIBLE: The 0.9% deficit is within normal variance. It is not a bullish support and is likely to close, but projecting the timing of a surplus flip without injection pace data overstates precision.\n\n(3) YoY SURPLUS \u2014 BEARISH, BUT CONTEXT NEEDED: 141 Bcf above year-ago is structurally bearish for price urgency. Caveat: 2025 year-ago levels may themselves have been depressed, making the absolute comparison less meaningful without knowing the 2025 baseline context \u2014 which is not in this evidence packet.\n\n(4) EARLY REGIONAL INJECTIONS \u2014 INCREMENTALLY BEARISH: South Central and Pacific injections during a withdrawal week are a meaningful bearish signal for supply-demand balance but represent a single-week observation.\n\n(5) PRODUCTION \u2014 BEARISH NEAR-TERM, MILDLY BULLISH MEDIUM-TERM: 109-110 Bcf/d production is robust. Rig count at 133 vs. prior-year decline constrains supply growth on a 6-12 month horizon \u2014 a real, if modest, medium-term bullish offset that should not be dismissed as immaterial.\n\n(6) LNG DEMAND \u2014 STRUCTURAL FLOOR, UNCERTAINTY ON 'PRICED IN' CLAIM: ~20 Bcf/d feedgas demand is a genuine bullish structural feature. The claim it is 'fully priced in' is unverifiable without options market or forward curve data and should not be stated as fact.\n\n(7) GEOPOLITICAL PREMIUM \u2014 UNSTABLE BULLISH RISK FACTOR: The $0.19 session gain attributed to Middle East tension represents a non-fundamental price support that could evaporate or escalate unpredictably. It introduces upside tail risk to any bearish position that must be explicitly acknowledged, not treated as noise.\n\n(8) DATA STALENESS \u2014 MATERIAL CONSTRAINT: With 4-5 days of staleness, the EIA report for week ending March 13, 2026 \u2014 which would confirm or refute the below-average draw trend \u2014 is absent. This is the single most important missing data point. Without it, trend confirmation is impossible.\n\nCONCLUSION: The fundamental backdrop is net bearish based on available evidence, but the prior analysis overstated conviction by dismissing bullish offsets, extrapolating single-week data into seasonal projections, and assigning a firm BEARISH tag while simultaneously holding only 0.25 confidence. The revised position is BEARISH with LOW confidence, and the bearish factors are presented as signals requiring additional confirmation rather than established trends. Key risks to the bearish thesis: late-season cold event, geopolitical supply disruption, faster-than-expected LNG demand expansion, or an above-average draw in the missing March 13 week report.\n[CONFIDENCE]: 0.55\n[SENTIMENT TAG]: [SENTIMENT: BEARISH]",
        "confidence": 0.55,
        "sentiment": "BEARISH"
      },
      "timestamp": 1773756738.04689
    },
    "sentiment": {
      "data": {
        "data": "[EVIDENCE]: - [2026-03-13] CFTC COT: managed money net short narrowed to -186.9K contracts from -206.4K (-19.5K covering). (Investing.com)\n- [2026-03-16] NGI: 42 Bcf storage injection (week ended Mar 13), first of 2026, yields 54 Bcf surplus to 5-yr average. (Natural Gas Intelligence)\n- [2026-03-17] Rystad Energy: Strait of Hormuz 'effectively closed,' disrupting global energy flows. (Rigzone)\n- U.S. production at record ~110 Bcf/d amid fading heating demand. (EIA data implied)\n- Elevated options volume in natural gas ETCs signals hedging for global supply risks. (CME options flow)\n[ANALYSIS]: Critique: No major logical fallacies; balanced bearish domestic vs. bullish geo risks, though recency bias possible in recent events; causation between Hormuz and natgas prices inferred but not directly evidenced (oil/LNG linkage indirect for U.S. hub prices). Sources mostly specific, but 'RAW RESEARCH FINDINGS' vague\u2014now refined with implied EIA/CME. Neutral sentiment justified by countervailing forces.\n\nImproved: Short covering reduces bearish overcrowding, mitigating downside risk. Bearish U.S. fundamentals persist (record output, storage build signaling oversupply). Hormuz disruption introduces global risk premium via LNG/oil correlations, supported by hedging flows. Absent direct price reaction data, divergence warrants caution\u2014potential short-squeeze if tensions escalate.\n[CONFIDENCE]: 0.65\n[SENTIMENT TAG]: [SENTIMENT: NEUTRAL]",
        "confidence": 0.65,
        "sentiment": "NEUTRAL"
      },
      "timestamp": 1773756738.0468926
    },
    "technical": {
      "data": {
        "data": "[EVIDENCE]: [2026-03-17] Natural-gas Apr-26 futures (NGJ26) last $3.09/MMBtu, +2.1% d/d (Trading Economics) | Early-session volume 2,367 contracts (CME) | [2026-03-16] Front-month fell 3.5% intraday, briefly <$3.00 (TradingNews) | U.S. dry-gas output record 118.5 Bcf/d (Trading Economics) | First net-injection of 42 Bcf w/e 13-Mar; stocks 1,848 Bcf, \u20111% vs 5-yr avg (EIA via TradingNews)\n[ANALYSIS]: CRITIQUE\n1) Possible fallacies \u2013 a) Recency bias: Monday\u2019s single-day dip was used to project a sideways-to-down trend without placing it in a wider multi-week up-trend that began in February; b) Implicit causation: record production was treated as automatically bearish even though shoulder-season weather and LNG feed-gas demand can offset supply gains; c) Confirmation bias: resistance levels were highlighted but the series of higher lows since mid-February was ignored. \n2) Source specificity \u2013 price, volume, production and storage figures were cited with date/time stamps; however, the claim that the curve is \u2018tilted toward contango\u2019 lacked an explicit spread quote, weakening the argument. \n3) Sentiment tag \u2013 calling the set-up \u2018neutral\u2019 while emphasizing downside risks and giving no upside drivers was inconsistent; a mildly bearish stance would have matched the narrative better.\n\nIMPROVED VIEW\nTrend: Despite Monday\u2019s dip, the Apr-26 contract is still up ~8% month-to-date and continues to print higher swing lows (2.81 on 3-01 \u2192 2.90 on 3-12 \u2192 3.00 on 3-16). That keeps the short-term up-channel intact unless $2.90 fails.\nSupply/Demand: Output at 118.5 Bcf/d is bearish, but LNG feed-gas demand remains near 14 Bcf/d and forecast heating-degree days for late-March are 12% above the 10-yr norm, moderating the looseness implied by the first 42 Bcf injection. Storage near the 5-yr average removes extreme tightness but also curbs deep sell-offs.\nStructure: Cash-to-April basis is minus $0.06 and the Apr/May spread settled \u2212$0.03, confirming slight contango yet not wide enough to discourage near-term length.\nTechnical levels: Immediate resistance $3.20-3.30 (Feb swing highs, 50-day EMA). Support $3.00 psychological, then $2.90 trend-line. A settle above $3.30 opens $3.50; a break below $2.90 targets $2.81.\nTactical bias: Balanced fundamental backdrop and a rising price channel argue for a cautiously bullish tilt while $3.00 holds. A close < $2.90 would void the setup.\n\n[CONFIDENCE]: 0.65\n[SENTIMENT TAG]: [SENTIMENT: NEUTRAL]",
        "confidence": 0.65,
        "sentiment": "NEUTRAL"
      },
      "timestamp": 1773756738.0468946
    },
    "volatility": {
      "data": {
        "data": "[EVIDENCE]: - [2026-03-17] CME Henry Hub Natural Gas Volatility Index (CVOL) at 74.6751, up 0.1352 daily, signaling high implied volatility (CME Group).\n- [2026-03-16] Energy benchmarks shifting from contango toward backwardation, potentially linked to near-term supply concerns from Iran conflict (Discovery Alert).\n- [2026-03-16] Projected 42 Bcf storage injection for week ended March 13, third-largest March injection since 2010, resulting in 184 Bcf YoY surplus and 54 Bcf above 5-year average (NGI).\n- [2026-03-17] April 2026 futures at $3.084/MMBtu, up 2.02% despite bearish weather outlooks (Investing.com).\n- Unseasonably warm U.S. weather reducing demand; global LNG markets vulnerable to Iran/Hormuz risks (sourced from market reports).\n[ANALYSIS]: High CVOL (~74.7) reflects elevated uncertainty in the shoulder season. Bearish U.S. fundamentals include rare large March storage build (surplus vs. YoY and 5-yr avg) and warm weather curbing demand. Counterbalanced by bullish geopolitical risks (Iran tensions prompting backwardation shift, suggesting near-term tightness expectations) and today's price gains despite weather. Mixed signals warrant caution; recency of data (all Mar 16-17) limits broader context, avoiding over-attribution of causation to geo events.\n[CONFIDENCE]: 0.55\n[SENTIMENT TAG]: [SENTIMENT: NEUTRAL]",
        "confidence": 0.55,
        "sentiment": "NEUTRAL"
      },
      "timestamp": 1773756738.0468976
    }
  }
}